manokit/__init__.py
manokit/exceptions.py
manokit-2.1.0.dist-info/LICENSE
manokit-2.1.0.dist-info/METADATA
manokit-2.1.0.dist-info/WHEEL
manokit-2.1.0.dist-info/top_level.txt
manokit-2.1.0.dist-info/RECORD
