Metadata-Version: 2.1
Name: manokit
Version: 2.1.0
Summary: An easy-to-use, purely native email sender
Home-page: https://github.com/nickythelion/manokit
Author: Nikolai Beloguzov
Author-email: Nikolai Beloguzov <nickythelionfurry@gmail.com>
License: GNU GENERAL PUBLIC LICENSE
Project-URL: Homepage, https://github.com/nickythelion/manokit
Project-URL: Changelog, https://github.com/nickythelion/manokit/blob/master/CHANGELOG.md
Project-URL: Repository, https://github.com/nickythelion/manokit
Keywords: email,manokit,smtp,network,communications,utility
Classifier: Development Status :: 5 - Production/Stable
Classifier: Environment :: Plugins
Classifier: Intended Audience :: Developers
Classifier: Intended Audience :: Information Technology
Classifier: Intended Audience :: Telecommunications Industry
Classifier: License :: OSI Approved :: GNU General Public License v3 or later (GPLv3+)
Classifier: Natural Language :: English
Classifier: Operating System :: OS Independent
Classifier: Programming Language :: Python
Classifier: Programming Language :: Python :: 3
Classifier: Programming Language :: Python :: 3 :: Only
Classifier: Programming Language :: Python :: 3.8
Classifier: Programming Language :: Python :: 3.9
Classifier: Programming Language :: Python :: 3.10
Classifier: Programming Language :: Python :: 3.11
Classifier: Topic :: Communications
Classifier: Topic :: Communications :: Email
Classifier: Topic :: Internet
Classifier: Topic :: Software Development
Classifier: Topic :: Software Development :: Libraries
Classifier: Topic :: Software Development :: Libraries :: Python Modules
Classifier: Topic :: System :: Networking
Classifier: Topic :: Utilities
Classifier: Typing :: Typed
Requires-Python: >=3.8
License-File: LICENSE
